{"authors_index.md":"PKh6fvxM","cards_adaptive_index.md":"D10UuFcJ","cards_alchemy_index.md":"bulCEaO2","cards_defense_game_index.md":"D-Ful4wz","cards_defense_game_random_index.md":"CKuXXaRE","cards_defense_index.md":"ntYfkcR_","cards_index.md":"C6FIz4b8","cards_integral_index.md":"B4OwmEi_","cards_nlp_index.md":"DAjdUN9O","cards_periods_index.md":"BueXY8d6","cards_positive_index.md":"B3D2S62G","cards_rebt_index.md":"CfKuf7a0","cards_spiral_index.md":"BiDmgOYz","cards_transact_index.md":"ihqvRPvd","cards_types_index.md":"COUGNa8H","field_areas_index.md":"DgWAXL67","field_index.md":"obDpeFIp","index.md":"CWLU7xBK","readme.md":"7xYhZgA_","support_index.md":"CxinwOur","synopsis_adaptive_index.md":"DmmqFABl","synopsis_defense_index.md":"Cyjm8s2h","synopsis_index.md":"B96RZfeO","synopsis_integral_index.md":"TdNNTR5N","synopsis_mandala_index.md":"B1C2BEXg","synopsis_nlp_index.md":"Dod90O2D","synopsis_periods_index.md":"DkD2yj_1","synopsis_positive_index.md":"CvARyWHs","synopsis_rebt_index.md":"BLIq3UIx","synopsis_transact_index.md":"BrRykWFI","synopsis_universal-strengths_index.md":"CneMkchX"}
